agent_actors/__init__.py
agent_actors/actors.py
agent_actors/agent.py
agent_actors/callback_manager.py
agent_actors/chains/__init__.py
agent_actors/chains/agent.py
agent_actors/chains/base.py
agent_actors/chains/child.py
agent_actors/chains/parent.py
agent_actors/child.py
agent_actors/models.py
agent_actors/parent.py
agent_actors/test_system.py
agent_actors/toolkit.py
agent_actors-0.1.0.dist-info/LICENSE
agent_actors-0.1.0.dist-info/METADATA
agent_actors-0.1.0.dist-info/WHEEL
agent_actors-0.1.0.dist-info/RECORD
