Metadata-Version: 2.1
Name: agent-actors
Version: 0.1.0
Summary: a proof-of-concept inspired by BabyAGI, the Plan-Do-Check-Adjust (PDCA) cycle, and the actor model of concurrency
License: BUSL-1.1
Author: Shaman AI
Author-email: hello@shaman.ai
Requires-Python: >=3.10.9,<4.0.0
Classifier: License :: Other/Proprietary License
Classifier: Programming Language :: Python :: 3
Classifier: Programming Language :: Python :: 3.11
Requires-Dist: aiohttp (>=3.8.4,<4.0.0)
Requires-Dist: gptcache (>=0.1.17,<0.2.0)
Requires-Dist: langchain (>=0.0.153,<0.0.154)
Requires-Dist: openai (>=0.27.4,<0.28.0)
Requires-Dist: pydantic (>=1.10.7,<2.0.0)
Requires-Dist: python-dotenv (>=1.0.0,<2.0.0)
Requires-Dist: ray[default] (>=2.3.1,<3.0.0)
Requires-Dist: termcolor (>=2.2.0,<3.0.0)
Requires-Dist: tiktoken (>=0.3.3,<0.4.0)
Requires-Dist: wikipedia (>=1.4.0,<2.0.0)
Requires-Dist: wolframalpha (>=5.0.0,<6.0.0)
